[{"name": "2023-02-01_389E75BB.jpg", "width": 750, "height": 500},
{"name": "2023-02-01_4A674945.jpg", "width": 500, "height": 559},
{"name": "2023-02-01_5DD867EB.jpg", "width": 578, "height": 431},
{"name": "2023-02-01_BF88C91F.jpg", "width": 510, "height": 500},
{"name": "2023-02-01_C51C5A36.jpg", "width": 591, "height": 499},
{"name": "2023-02-01_C96B75CA.jpg", "width": 533, "height": 500},
{"name": "2023-02-01_D495CB5E.jpg", "width": 607, "height": 499},
{"name": "2023-02-01_D5CFF7CF.jpg", "width": 500, "height": 581},
{"name": "2023-02-01_D869B448.jpg", "width": 582, "height": 500},
{"name": "2023-02-01_D9FAE25A.jpg", "width": 500, "height": 625},
{"name": "2023-02-01_F2A66BC1.jpg", "width": 694, "height": 360},
{"name": "2023-02-02_256AD1BE.jpg", "width": 500, "height": 500},
{"name": "2023-02-02_2F4B5096.jpg", "width": 500, "height": 500},
{"name": "2023-02-02_4FAFF0A2.jpg", "width": 666, "height": 500},
{"name": "2023-02-02_642FFB95.jpg", "width": 500, "height": 543},
{"name": "2023-02-02_99625CFC.jpg", "width": 577, "height": 433},
{"name": "2023-02-02_9A1B30F7.jpg", "width": 500, "height": 656},
{"name": "2023-02-02_9C46F572.jpg", "width": 500, "height": 819},
{"name": "2023-02-02_B8CAA7C5.jpg", "width": 635, "height": 393},
{"name": "2023-02-02_C69E0ACB.jpg", "width": 500, "height": 535},
{"name": "2023-02-02_D0E9B647.jpg", "width": 500, "height": 486},
{"name": "2023-02-02_DFF9710D.jpg", "width": 582, "height": 500},
{"name": "2023-02-03_2214798E.jpg", "width": 526, "height": 499},
{"name": "2023-02-03_5459F51E.jpg", "width": 567, "height": 500},
{"name": "2023-02-03_57C0762A.jpg", "width": 616, "height": 499},
{"name": "2023-02-03_73191A95.jpg", "width": 500, "height": 523},
{"name": "2023-02-03_8ACE92FC.jpg", "width": 516, "height": 500},
{"name": "2023-02-03_A719FEC9.jpg", "width": 499, "height": 471},
{"name": "2023-02-03_B7CD5CB5.jpg", "width": 539, "height": 486},
{"name": "2023-02-03_BF3EE17D.jpg", "width": 500, "height": 500},
{"name": "2023-02-03_D8C11735.jpg", "width": 500, "height": 601},
{"name": "2023-02-03_EA7EEEFE.jpg", "width": 634, "height": 499},
{"name": "2023-02-03_F01FDE01.jpg", "width": 500, "height": 623},
{"name": "2023-02-04_19BD718A.jpg", "width": 500, "height": 558},
{"name": "2023-02-04_5583E4AF.jpg", "width": 544, "height": 459},
{"name": "2023-02-04_5AF89088.jpg", "width": 500, "height": 521},
{"name": "2023-02-04_6E6C85E4.jpg", "width": 500, "height": 709},
{"name": "2023-02-04_7117F70D.jpg", "width": 500, "height": 614},
{"name": "2023-02-04_81779231.jpg", "width": 500, "height": 625},
{"name": "2023-02-04_97810C79.jpg", "width": 622, "height": 500},
{"name": "2023-02-04_B39B105E.jpg", "width": 500, "height": 507},
{"name": "2023-02-04_B6557D7B.jpg", "width": 502, "height": 500},
{"name": "2023-02-04_E45FBAE9.jpg", "width": 500, "height": 500},
{"name": "2023-02-04_F79A8520.jpg", "width": 1636, "height": 1200},
{"name": "2023-02-05_09ED1473.jpg", "width": 547, "height": 458},
{"name": "2023-02-05_487B4762.jpg", "width": 515, "height": 439},
{"name": "2023-02-05_4B7A13C1.jpg", "width": 500, "height": 611},
{"name": "2023-02-05_776C1ED4.jpg", "width": 538, "height": 499},
{"name": "2023-02-05_975166C3.jpg", "width": 577, "height": 432},
{"name": "2023-02-05_9F6606B2.jpg", "width": 664, "height": 376},
{"name": "2023-02-05_CFBEB174.jpg", "width": 749, "height": 500},
{"name": "2023-02-05_E2E4DD04.jpg", "width": 555, "height": 450},
{"name": "2023-02-05_E5CB7B51.jpg", "width": 626, "height": 481},
{"name": "2023-02-05_F21423DB.jpg", "width": 538, "height": 500},
{"name": "2023-02-05_F8B67E80.jpg", "width": 500, "height": 608},
{"name": "2023-02-06_2F159264.jpg", "width": 533, "height": 500},
{"name": "2023-02-06_3157E5A6.jpg", "width": 524, "height": 499},
{"name": "2023-02-06_3C56A70D.jpg", "width": 620, "height": 485},
{"name": "2023-02-06_5BB82817.jpg", "width": 500, "height": 748},
{"name": "2023-02-06_749B3B27.jpg", "width": 500, "height": 540},
{"name": "2023-02-06_8AD6ED22.jpg", "width": 591, "height": 422},
{"name": "2023-02-06_8B483D25.jpg", "width": 720, "height": 480},
{"name": "2023-02-06_8E7B9FDC.jpg", "width": 584, "height": 427},
{"name": "2023-02-06_CE7D1231.jpg", "width": 500, "height": 816},
{"name": "2023-02-06_D4055E92.jpg", "width": 2676, "height": 1176},
{"name": "2023-02-06_F013CD38.jpg", "width": 593, "height": 500},
{"name": "2023-02-07_2D4ACF03.jpg", "width": 500, "height": 508},
{"name": "2023-02-07_42D13110.jpg", "width": 720, "height": 679},
{"name": "2023-02-07_48A549E3.jpg", "width": 680, "height": 543},
{"name": "2023-02-07_695D622C.jpg", "width": 500, "height": 680},
{"name": "2023-02-07_74474849.jpg", "width": 500, "height": 585},
{"name": "2023-02-07_75847414.jpg", "width": 513, "height": 500},
{"name": "2023-02-07_94E7BEF8.jpg", "width": 500, "height": 635},
{"name": "2023-02-07_A82BD46F.jpg", "width": 500, "height": 625},
{"name": "2023-02-07_AA9BD5E0.jpg", "width": 500, "height": 666},
{"name": "2023-02-07_B0F0AE46.jpg", "width": 750, "height": 500},
{"name": "2023-02-07_D85FD8D3.jpg", "width": 500, "height": 562},
{"name": "2023-02-08_03985D6E.jpg", "width": 743, "height": 500},
{"name": "2023-02-08_18083717.jpg", "width": 850, "height": 400},
{"name": "2023-02-08_330FED53.jpg", "width": 581, "height": 429},
{"name": "2023-02-08_383AC3BB.jpg", "width": 597, "height": 500},
{"name": "2023-02-08_6E9B6F1E.jpg", "width": 500, "height": 535},
{"name": "2023-02-08_952BA0AD.jpg", "width": 749, "height": 500},
{"name": "2023-02-08_98866AF5.jpg", "width": 612, "height": 499},
{"name": "2023-02-08_A0955C05.jpg", "width": 600, "height": 500},
{"name": "2023-02-08_C262D4A5.jpg", "width": 800, "height": 432},
{"name": "2023-02-08_C89990A1.jpg", "width": 625, "height": 400},
{"name": "2023-02-08_F6B0C8C8.jpg", "width": 500, "height": 500},
{"name": "2023-02-09_174ACC82.jpg", "width": 500, "height": 625},
{"name": "2023-02-09_1F1CD92D.jpg", "width": 644, "height": 500},
{"name": "2023-02-09_313761A1.jpg", "width": 613, "height": 499},
{"name": "2023-02-09_3BAF7A58.jpg", "width": 761, "height": 499},
{"name": "2023-02-09_3F8F1992.jpg", "width": 500, "height": 642},
{"name": "2023-02-09_4097C6EE.jpg", "width": 674, "height": 370},
{"name": "2023-02-09_5A05AF7D.jpg", "width": 500, "height": 530},
{"name": "2023-02-09_AD0FCEC8.jpg", "width": 500, "height": 1003},
{"name": "2023-02-09_CC7D84D5.jpg", "width": 592, "height": 482},
{"name": "2023-02-09_EF40234F.jpg", "width": 534, "height": 500},
{"name": "2023-02-09_FC818486.jpg", "width": 500, "height": 624},
{"name": "2023-02-10_058CCDDA.jpg", "width": 541, "height": 500},
{"name": "2023-02-10_094A9CDF.jpg", "width": 500, "height": 523},
{"name": "2023-02-10_325062D7.jpg", "width": 518, "height": 499},
{"name": "2023-02-10_46F2267F.jpg", "width": 547, "height": 482},
{"name": "2023-02-10_4B145AF9.jpg", "width": 503, "height": 500},
{"name": "2023-02-10_5A3872CC.jpg", "width": 820, "height": 461},
{"name": "2023-02-10_610193DE.jpg", "width": 889, "height": 475},
{"name": "2023-02-10_8B32B993.jpg", "width": 500, "height": 538},
{"name": "2023-02-10_93D1CC27.jpg", "width": 503, "height": 499},
{"name": "2023-02-10_9A0861C7.jpg", "width": 500, "height": 556},
{"name": "2023-02-10_C36DD422.jpg", "width": 500, "height": 644},
{"name": "2023-02-11_08ACC049.jpg", "width": 500, "height": 560},
{"name": "2023-02-11_1A32E2F9.jpg", "width": 750, "height": 341},
{"name": "2023-02-11_1BB4A57B.jpg", "width": 680, "height": 515},
{"name": "2023-02-11_1E5C88D3.jpg", "width": 680, "height": 363},
{"name": "2023-02-11_23571A83.jpg", "width": 523, "height": 500},
{"name": "2023-02-11_7A74DA97.jpg", "width": 592, "height": 500},
{"name": "2023-02-11_A5DBEFEE.jpg", "width": 740, "height": 499},
{"name": "2023-02-11_A82FD4C9.jpg", "width": 657, "height": 500},
{"name": "2023-02-11_BAF1203B.jpg", "width": 680, "height": 421},
{"name": "2023-02-11_FE65CD1E.jpg", "width": 507, "height": 500},
{"name": "2023-02-11_FEF65BE8.jpg", "width": 657, "height": 500},
{"name": "2023-02-12_1A00526B.jpg", "width": 517, "height": 500},
{"name": "2023-02-12_216E4F6B.jpg", "width": 624, "height": 400},
{"name": "2023-02-12_4226CC71.jpg", "width": 360, "height": 617},
{"name": "2023-02-12_834EA1ED.jpg", "width": 514, "height": 499},
{"name": "2023-02-12_87E9AD24.jpg", "width": 500, "height": 520},
{"name": "2023-02-12_9D9FC15C.jpg", "width": 678, "height": 500},
{"name": "2023-02-12_A33DC549.jpg", "width": 622, "height": 401},
{"name": "2023-02-12_C9A35E4C.jpg", "width": 525, "height": 500},
{"name": "2023-02-12_CF25FBE8.jpg", "width": 500, "height": 1062},
{"name": "2023-02-12_D7F09E2D.jpg", "width": 552, "height": 452},
{"name": "2023-02-12_E588C611.jpg", "width": 533, "height": 500},
{"name": "2023-02-13_470521C1.jpg", "width": 600, "height": 499},
{"name": "2023-02-13_5AA52FD3.jpg", "width": 676, "height": 680},
{"name": "2023-02-13_6336B030.jpg", "width": 500, "height": 550},
{"name": "2023-02-13_67994A91.jpg", "width": 500, "height": 536},
{"name": "2023-02-13_7AEAAFC1.jpg", "width": 689, "height": 500},
{"name": "2023-02-13_8BA2452F.jpg", "width": 520, "height": 457},
{"name": "2023-02-13_91AEE96A.jpg", "width": 640, "height": 480},
{"name": "2023-02-13_AAE92A7A.jpg", "width": 523, "height": 500},
{"name": "2023-02-13_AE307BA0.jpg", "width": 500, "height": 514},
{"name": "2023-02-13_C1469A76.jpg", "width": 537, "height": 500},
{"name": "2023-02-13_D92581B9.jpg", "width": 807, "height": 646},
{"name": "2023-02-14_0E89EE5D.jpg", "width": 641, "height": 499},
{"name": "2023-02-14_398C2848.jpg", "width": 500, "height": 600},
{"name": "2023-02-14_5A5DC71F.jpg", "width": 599, "height": 500},
{"name": "2023-02-14_5F0E5F3C.jpg", "width": 500, "height": 634},
{"name": "2023-02-14_648C83E7.jpg", "width": 672, "height": 500},
{"name": "2023-02-14_7F5C081F.jpg", "width": 644, "height": 500},
{"name": "2023-02-14_91CB745F.jpg", "width": 500, "height": 545},
{"name": "2023-02-14_9907DEA1.jpg", "width": 500, "height": 562},
{"name": "2023-02-14_A1C1DD7F.jpg", "width": 788, "height": 444},
{"name": "2023-02-14_D980485C.jpg", "width": 500, "height": 595},
{"name": "2023-02-14_FA4C122C.jpg", "width": 500, "height": 591},
{"name": "2023-02-15_00370634.jpg", "width": 500, "height": 573},
{"name": "2023-02-15_04AFEE4B.jpg", "width": 526, "height": 500},
{"name": "2023-02-15_2AEA5069.jpg", "width": 500, "height": 522},
{"name": "2023-02-15_48AD614A.jpg", "width": 752, "height": 500},
{"name": "2023-02-15_5743A3E8.jpg", "width": 500, "height": 500},
{"name": "2023-02-15_892D17D5.jpg", "width": 521, "height": 479},
{"name": "2023-02-15_E450C4A3.jpg", "width": 500, "height": 674},
{"name": "2023-02-15_EE1FFBBC.jpg", "width": 509, "height": 500},
{"name": "2023-02-15_F0365BFA.jpg", "width": 500, "height": 521},
{"name": "2023-02-15_F560555E.jpg", "width": 509, "height": 500},
{"name": "2023-02-15_F8E0E637.jpg", "width": 500, "height": 669},
{"name": "2023-02-16_0EC66590.jpg", "width": 576, "height": 433},
{"name": "2023-02-16_10E56062.jpg", "width": 677, "height": 369},
{"name": "2023-02-16_2B663EA0.jpg", "width": 765, "height": 663},
{"name": "2023-02-16_2C7DF6E8.jpg", "width": 619, "height": 680},
{"name": "2023-02-16_3D60780B.jpg", "width": 550, "height": 500},
{"name": "2023-02-16_52075ACD.jpg", "width": 559, "height": 499},
{"name": "2023-02-16_7CB99B80.jpg", "width": 532, "height": 477},
{"name": "2023-02-16_93CFB2FC.jpg", "width": 500, "height": 593},
{"name": "2023-02-16_A2E251B2.jpg", "width": 500, "height": 565},
{"name": "2023-02-16_B8E6D5B3.jpg", "width": 749, "height": 500},
{"name": "2023-02-16_C74C4F7B.jpg", "width": 1928, "height": 1880},
{"name": "2023-02-17_0F1BD16F.jpg", "width": 565, "height": 441},
{"name": "2023-02-17_2226C936.jpg", "width": 500, "height": 500},
{"name": "2023-02-17_2703A9D0.jpg", "width": 513, "height": 500},
{"name": "2023-02-17_34586B8D.jpg", "width": 500, "height": 633},
{"name": "2023-02-17_54492638.jpg", "width": 624, "height": 400},
{"name": "2023-02-17_67765E81.jpg", "width": 500, "height": 624},
{"name": "2023-02-17_83C92C86.jpg", "width": 500, "height": 645},
{"name": "2023-02-17_95F73DBC.jpg", "width": 578, "height": 432},
{"name": "2023-02-17_E44534C7.jpg", "width": 797, "height": 500},
{"name": "2023-02-17_E64321F9.jpg", "width": 729, "height": 493},
{"name": "2023-02-17_EAF56ECD.jpg", "width": 500, "height": 500},
{"name": "2023-02-18_011BDF39.jpg", "width": 658, "height": 500},
{"name": "2023-02-18_03764B4D.jpg", "width": 2100, "height": 1313},
{"name": "2023-02-18_0E02AD94.jpg", "width": 679, "height": 455},
{"name": "2023-02-18_1EBEF533.jpg", "width": 500, "height": 708},
{"name": "2023-02-18_632A5C45.jpg", "width": 750, "height": 500},
{"name": "2023-02-18_70779D20.jpg", "width": 529, "height": 471},
{"name": "2023-02-18_72CC9007.jpg", "width": 511, "height": 488},
{"name": "2023-02-18_7BD66820.jpg", "width": 535, "height": 466},
{"name": "2023-02-18_9F720B1A.jpg", "width": 500, "height": 565},
{"name": "2023-02-18_E6DEB323.jpg", "width": 500, "height": 691},
{"name": "2023-02-18_FD4E9DD5.jpg", "width": 552, "height": 452},
{"name": "2023-02-19_22AACBA0.jpg", "width": 534, "height": 467},
{"name": "2023-02-19_24384714.jpg", "width": 680, "height": 442},
{"name": "2023-02-19_5F448C39.jpg", "width": 500, "height": 544},
{"name": "2023-02-19_765FCC8A.jpg", "width": 730, "height": 500},
{"name": "2023-02-19_A31EA88D.jpg", "width": 500, "height": 622},
{"name": "2023-02-19_DE3EEADE.jpg", "width": 518, "height": 500},
{"name": "2023-02-19_E3B4FF6F.jpg", "width": 680, "height": 433},
{"name": "2023-02-19_FB3CF3DD.jpg", "width": 577, "height": 433},
{"name": "2023-02-19_FC445A96.jpg", "width": 679, "height": 491},
{"name": "2023-02-19_FF084479.jpg", "width": 680, "height": 391},
{"name": "2023-02-19_FFF73418.jpg", "width": 500, "height": 623},
{"name": "2023-02-20_2FCFC0B8.jpg", "width": 500, "height": 654},
{"name": "2023-02-20_60B3A214.jpg", "width": 500, "height": 499},
{"name": "2023-02-20_67ACE625.jpg", "width": 777, "height": 500},
{"name": "2023-02-20_6CEF78CF.jpg", "width": 528, "height": 499},
{"name": "2023-02-20_7C200C2D.jpg", "width": 658, "height": 499},
{"name": "2023-02-20_7DE128C4.jpg", "width": 500, "height": 500},
{"name": "2023-02-20_894DCA2A.jpg", "width": 559, "height": 446},
{"name": "2023-02-20_C03D44A4.jpg", "width": 500, "height": 503},
{"name": "2023-02-20_C70CB01F.jpg", "width": 617, "height": 499},
{"name": "2023-02-20_E58ADE9C.jpg", "width": 502, "height": 500},
{"name": "2023-02-20_EC52A124.jpg", "width": 565, "height": 500},
{"name": "2023-02-21_0DEA918A.jpg", "width": 500, "height": 491},
{"name": "2023-02-21_2C06F898.jpg", "width": 612, "height": 408},
{"name": "2023-02-21_2C5D3C3A.jpg", "width": 579, "height": 500},
{"name": "2023-02-21_3A14F5C1.jpg", "width": 500, "height": 679},
{"name": "2023-02-21_6FF56A25.jpg", "width": 554, "height": 500},
{"name": "2023-02-21_73F7799E.jpg", "width": 500, "height": 539},
{"name": "2023-02-21_93049CA4.jpg", "width": 680, "height": 474},
{"name": "2023-02-21_9B3E4F37.jpg", "width": 500, "height": 477},
{"name": "2023-02-21_BC7399E5.jpg", "width": 575, "height": 500},
{"name": "2023-02-21_CBC9A610.jpg", "width": 500, "height": 582},
{"name": "2023-02-21_E082BAA7.jpg", "width": 517, "height": 499},
{"name": "2023-02-22_08BD9ACA.jpg", "width": 679, "height": 478},
{"name": "2023-02-22_09BBA7B6.jpg", "width": 500, "height": 880},
{"name": "2023-02-22_0BC363BF.jpg", "width": 500, "height": 508},
{"name": "2023-02-22_1FF8B2D1.jpg", "width": 596, "height": 438},
{"name": "2023-02-22_3FD41A11.jpg", "width": 512, "height": 500},
{"name": "2023-02-22_4426B583.jpg", "width": 500, "height": 562},
{"name": "2023-02-22_6CF6F3EB.jpg", "width": 500, "height": 505},
{"name": "2023-02-22_A5045A29.jpg", "width": 500, "height": 500},
{"name": "2023-02-22_C75C1ABF.jpg", "width": 888, "height": 499},
{"name": "2023-02-22_CB3177BE.jpg", "width": 500, "height": 537},
{"name": "2023-02-22_E245D9A0.jpg", "width": 669, "height": 500},
{"name": "2023-02-23_0477E058.jpg", "width": 500, "height": 629},
{"name": "2023-02-23_141A439D.jpg", "width": 577, "height": 433},
{"name": "2023-02-23_31C79287.jpg", "width": 577, "height": 433},
{"name": "2023-02-23_32413A99.jpg", "width": 531, "height": 604},
{"name": "2023-02-23_73175948.jpg", "width": 886, "height": 499},
{"name": "2023-02-23_73EAD2D3.jpg", "width": 691, "height": 500},
{"name": "2023-02-23_8C7416CB.jpg", "width": 500, "height": 690},
{"name": "2023-02-23_A097FA5B.jpg", "width": 500, "height": 1406},
{"name": "2023-02-23_A95AC40E.jpg", "width": 507, "height": 500},
{"name": "2023-02-23_C66F7FA1.jpg", "width": 577, "height": 433},
{"name": "2023-02-23_CB221767.jpg", "width": 684, "height": 500},
{"name": "2023-02-24_013DA6DA.jpg", "width": 500, "height": 589},
{"name": "2023-02-24_1A6B4245.jpg", "width": 500, "height": 532},
{"name": "2023-02-24_3984546C.jpg", "width": 590, "height": 500},
{"name": "2023-02-24_50C40C07.jpg", "width": 500, "height": 596},
{"name": "2023-02-24_79D2EC9E.jpg", "width": 500, "height": 513},
{"name": "2023-02-24_7FD5BC4E.jpg", "width": 537, "height": 500},
{"name": "2023-02-24_9E15178A.jpg", "width": 500, "height": 537},
{"name": "2023-02-24_A34435DA.jpg", "width": 621, "height": 500},
{"name": "2023-02-24_C2FACAE1.jpg", "width": 500, "height": 583},
{"name": "2023-02-24_CBACD724.jpg", "width": 729, "height": 500},
{"name": "2023-02-24_D56A82E3.jpg", "width": 593, "height": 500},
{"name": "2023-02-25_095B5679.jpg", "width": 500, "height": 503},
{"name": "2023-02-25_09CF8C99.jpg", "width": 720, "height": 509},
{"name": "2023-02-25_0E0E1A5E.jpg", "width": 500, "height": 854},
{"name": "2023-02-25_1D2828F1.jpg", "width": 627, "height": 398},
{"name": "2023-02-25_499B5D69.jpg", "width": 640, "height": 480},
{"name": "2023-02-25_72F37164.jpg", "width": 680, "height": 408},
{"name": "2023-02-25_9CFAA4DA.jpg", "width": 680, "height": 460},
{"name": "2023-02-25_AA887BFF.jpg", "width": 600, "height": 451},
{"name": "2023-02-25_D82962FB.jpg", "width": 561, "height": 500},
{"name": "2023-02-25_D87E2B89.jpg", "width": 591, "height": 500},
{"name": "2023-02-25_FD4BE67D.jpg", "width": 627, "height": 500},
{"name": "2023-02-26_0756AC3E.jpg", "width": 500, "height": 621},
{"name": "2023-02-26_33F7B7F7.jpg", "width": 657, "height": 500},
{"name": "2023-02-26_59D8DC2A.jpg", "width": 500, "height": 500},
{"name": "2023-02-26_7FDB7F53.jpg", "width": 500, "height": 562},
{"name": "2023-02-26_8E652A67.jpg", "width": 500, "height": 568},
{"name": "2023-02-26_A6B899C3.jpg", "width": 500, "height": 576},
{"name": "2023-02-26_B8FD620F.jpg", "width": 501, "height": 499},
{"name": "2023-02-26_CEDD5F50.jpg", "width": 634, "height": 500},
{"name": "2023-02-26_DB1F1849.jpg", "width": 500, "height": 666},
{"name": "2023-02-26_EED4ADC3.jpg", "width": 505, "height": 494},
{"name": "2023-02-26_FDD7954C.jpg", "width": 619, "height": 499},
{"name": "2023-02-27_1C2225BA.jpg", "width": 539, "height": 500},
{"name": "2023-02-27_41F6FEE1.jpg", "width": 500, "height": 560},
{"name": "2023-02-27_634604E7.jpg", "width": 661, "height": 499},
{"name": "2023-02-27_720C0333.jpg", "width": 500, "height": 839},
{"name": "2023-02-27_75919F66.jpg", "width": 545, "height": 500},
{"name": "2023-02-27_94B924DD.jpg", "width": 500, "height": 796},
{"name": "2023-02-27_A81737D3.jpg", "width": 400, "height": 400},
{"name": "2023-02-27_BB672357.jpg", "width": 500, "height": 585},
{"name": "2023-02-27_E300B8F4.jpg", "width": 540, "height": 500},
{"name": "2023-02-27_F66FA739.jpg", "width": 671, "height": 500},
{"name": "2023-02-27_F8830819.jpg", "width": 504, "height": 500},
{"name": "2023-02-28_0093F81B.jpg", "width": 600, "height": 422},
{"name": "2023-02-28_015D26C0.jpg", "width": 500, "height": 549},
{"name": "2023-02-28_5514BB67.jpg", "width": 540, "height": 462},
{"name": "2023-02-28_5BEAC301.jpg", "width": 500, "height": 658},
{"name": "2023-02-28_86055212.jpg", "width": 809, "height": 499},
{"name": "2023-02-28_877789D4.jpg", "width": 500, "height": 575},
{"name": "2023-02-28_A5A50F27.jpg", "width": 503, "height": 500},
{"name": "2023-02-28_AFF5DA60.jpg", "width": 504, "height": 499},
{"name": "2023-02-28_BA442C58.jpg", "width": 500, "height": 843},
{"name": "2023-02-28_F2FC7426.jpg", "width": 597, "height": 500},
{"name": "2023-02-28_FBB5B992.jpg", "width": 857, "height": 375}]